dagster_delta_polars/__init__.py
dagster_delta_polars/deltalake_polars_type_handler.py
dagster_delta_polars/py.typed
dagster_delta_polars/lakefs_io/__init__.py
dagster_delta_polars/lakefs_io/deltalake_polars_lakefs_type_handler.py
dagster_delta_polars/lakefs_io/lakefs_client_resource.py
dagster_delta_polars-0.2.0.dist-info/LICENSE
dagster_delta_polars-0.2.0.dist-info/METADATA
dagster_delta_polars-0.2.0.dist-info/WHEEL
dagster_delta_polars-0.2.0.dist-info/top_level.txt
dagster_delta_polars-0.2.0.dist-info/RECORD
