Metadata-Version: 2.2
Name: dagster-delta-polars
Version: 0.2.0
Summary: Polars deltalake IO Managers for Dagster with optional LakeFS support
Author-email: Ion Koutsouris <15728914+ion-elgreco@users.noreply.github.com>, Stefan Verbruggen <27513235+sverbruggen@users.noreply.github.com>
Keywords: dagster,deltalake,delta,polars,lakefs,datalake,io manager
Classifier: License :: OSI Approved :: Apache Software License
Classifier: Programming Language :: Python :: 3.9
Classifier: Programming Language :: Python :: 3.10
Classifier: Programming Language :: Python :: 3.11
Classifier: Programming Language :: Python :: 3.12
Requires-Python: >=3.9
License-File: LICENSE
Requires-Dist: dagster-delta
Requires-Dist: Deprecated
Provides-Extra: lakefs
Requires-Dist: lakefs; extra == "lakefs"
